LICENSE.txt
MANIFEST.in
README.md
setup.py
daemonize/__init__.py
daemonize/daemon.py
smart_suspend/__init__.py
smart_suspend/commandline.py
smart_suspend/smart_suspend.py
snowflake_config/__init__.py
snowflake_config/snowflake_configuration.py
snowflake_smart_suspend.egg-info/PKG-INFO
snowflake_smart_suspend.egg-info/SOURCES.txt
snowflake_smart_suspend.egg-info/dependency_links.txt
snowflake_smart_suspend.egg-info/entry_points.txt
snowflake_smart_suspend.egg-info/not-zip-safe
snowflake_smart_suspend.egg-info/requires.txt
snowflake_smart_suspend.egg-info/top_level.txt