Metadata-Version: 1.1
Name: snowflake-smart-suspend
Version: 0.1.2
Summary: Unix service to suspend the snowflake warehouses smartly to cut the cost.
Home-page: https://github.com/samarthg/snowflake-smart-suspend
Author: Samarth Gahire
Author-email: samarth.gahire@gmail.com
License: MIT
Download-URL: https://github.com/samarthg/snowflake-smart-suspend/archive/v0.1.2.tar.gz
Keywords: snowflake,warehouse,optimization,cost
Platform: UNKNOWN
Classifier: Development Status :: 4 - Beta
Classifier: Intended Audience :: Developers
Classifier: Programming Language :: Python :: 3
